certbot_dns_duckdns/__init__.py
certbot_dns_duckdns/cert/__init__.py
certbot_dns_duckdns/cert/client.py
certbot_dns_duckdns/duckdns/__init__.py
certbot_dns_duckdns/duckdns/client.py
certbot_dns_duckdns-1.7.0.dist-info/METADATA
certbot_dns_duckdns-1.7.0.dist-info/WHEEL
certbot_dns_duckdns-1.7.0.dist-info/entry_points.txt
certbot_dns_duckdns-1.7.0.dist-info/top_level.txt
certbot_dns_duckdns-1.7.0.dist-info/RECORD
