Metadata-Version: 2.4
Name: certbot_dns_duckdns
Version: 1.7.0
Summary: Obtain certificates using a DNS TXT record for DuckDNS domains
Home-page: https://github.com/infinityofspace/certbot_dns_duckdns
Author: infinityofspace
License: MIT
Classifier: Development Status :: 5 - Production/Stable
Classifier: Programming Language :: Python :: 3
Classifier: Programming Language :: Python :: 3.10
Classifier: Programming Language :: Python :: 3.11
Classifier: Programming Language :: Python :: 3.12
Classifier: Programming Language :: Python :: 3.13
Classifier: Programming Language :: Python :: 3.14
Classifier: License :: OSI Approved :: MIT License
Classifier: Topic :: Security
Classifier: Topic :: Internet :: WWW/HTTP
Classifier: Topic :: Utilities
Classifier: Topic :: System :: Systems Administration
Requires-Python: >=3.10
Requires-Dist: certbot<6.0,>=1.18.0
Requires-Dist: requests<3.0,>=2.20.0
Requires-Dist: dnspython<3.0,>=2.0.0
Dynamic: author
Dynamic: classifier
Dynamic: description
Dynamic: description-content-type
Dynamic: home-page
Dynamic: license
Dynamic: requires-dist
Dynamic: requires-python
Dynamic: summary
